tablature/__init__.py
tablature/views.py
tablature/jinja2/tablature/table_page.html
tablature/jinja2/tablature/includes/table.html
tablature/locale/fr/LC_MESSAGES/django.mo
tablature/locale/fr/LC_MESSAGES/django.po
tablature/static/js/tablature.js
tablature/static/less/tablature.less
tablature/templates/tablature/table_page.html
tablature/templates/tablature/includes/table.html
django_tablature-0.2.3.dist-info/LICENSE
django_tablature-0.2.3.dist-info/METADATA
django_tablature-0.2.3.dist-info/WHEEL
django_tablature-0.2.3.dist-info/top_level.txt
django_tablature-0.2.3.dist-info/RECORD
